skyplatform_iam/__init__.py
skyplatform_iam/config.py
skyplatform_iam/connect_agenterra_iam.py
skyplatform_iam/exceptions.py
skyplatform_iam/middleware.py
skyplatform_iam-1.2.4.dist-info/METADATA
skyplatform_iam-1.2.4.dist-info/WHEEL
skyplatform_iam-1.2.4.dist-info/RECORD
