Metadata-Version: 2.4
Name: skyplatform-iam
Version: 1.2.4
Summary: SkyPlatform IAM认证SDK，提供FastAPI中间件和认证路由
Project-URL: Homepage, https://github.com/xinmayoujiang12621/agenterra_iam
Project-URL: Documentation, https://skyplatform-iam.readthedocs.io/
Project-URL: Repository, https://github.com/xinmayoujiang12621/agenterra_iam.git
Project-URL: Issues, https://github.com/xinmayoujiang12621/agenterra_iam/issues
Project-URL: Changelog, https://github.com/xinmayoujiang12621/agenterra_iam/blob/main/CHANGELOG.md
Author-email: x9 <xuanxienanxunmobao@gmail.com>
License: MIT
Keywords: authentication,fastapi,iam,middleware,skyplatform
Classifier: Development Status :: 5 - Production/Stable
Classifier: Framework :: FastAPI
Classifier: Intended Audience :: Developers
Classifier: License :: OSI Approved :: MIT License
Classifier: Operating System :: OS Independent
Classifier: Programming Language :: Python :: 3
Classifier: Programming Language :: Python :: 3.8
Classifier: Programming Language :: Python :: 3.9
Classifier: Programming Language :: Python :: 3.10
Classifier: Programming Language :: Python :: 3.11
Classifier: Programming Language :: Python :: 3.12
Classifier: Topic :: Internet :: WWW/HTTP :: HTTP Servers
Classifier: Topic :: Security
Classifier: Topic :: Software Development :: Libraries :: Python Modules
Requires-Python: >=3.9
Requires-Dist: fastapi>=0.68.0
Requires-Dist: pydantic>=1.8.0
Requires-Dist: pyjwt>=2.10.1
Requires-Dist: requests>=2.25.0
Requires-Dist: starlette>=0.14.0
Provides-Extra: dev
Requires-Dist: black>=22.0.0; extra == 'dev'
Requires-Dist: flake8>=4.0.0; extra == 'dev'
Requires-Dist: httpx>=0.23.0; extra == 'dev'
Requires-Dist: isort>=5.10.0; extra == 'dev'
Requires-Dist: mypy>=0.950; extra == 'dev'
Requires-Dist: pytest-asyncio>=0.18.0; extra == 'dev'
Requires-Dist: pytest>=6.0.0; extra == 'dev'
